{
  "cases": {
    "step_5cm": {
      "seed": 2037952871,
      "step_height_m": 0.05,
      "step_x_m": 0.22,
      "row_metrics": {
        "terrain_type": "step_5cm",
        "seed": 2037952871,
        "terrain_height_delta_m": 0.05000000074505806,
        "centerline_height_delta_m": 0.05000000074505806,
        "step_transition_width_m": 0.0,
        "step_on_vehicle_path": true,
        "front_wheel_first_reach_step_time_s": 0.35999998450279236,
        "progress": 1.013389229774475,
        "pitch_max_rad": 0.2885250151157379,
        "slip_p95": 0.08540560646499476,
        "bottom_contact_rate": 0.0,
        "q_lift": 0.10833334177732468,
        "q_pitch": 0.7514211659127302,
        "q_slip": 0.05292088240385055,
        "chassis_min_clearance_m": 0.05000000074505806,
        "wheel_min_clearance_m": -0.05000000074505806,
        "fail_reason": "-"
      },
      "centerline_profile": [
        [
          -0.4,
          0.0
        ],
        [
          -0.38,
          0.0
        ],
        [
          -0.36000000000000004,
          0.0
        ],
        [
          -0.34,
          0.0
        ],
        [
          -0.32,
          0.0
        ],
        [
          -0.30000000000000004,
          0.0
        ],
        [
          -0.28,
          0.0
        ],
        [
          -0.26,
          0.0
        ],
        [
          -0.24000000000000002,
          0.0
        ],
        [
          -0.22000000000000003,
          0.0
        ],
        [
          -0.2,
          0.0
        ],
        [
          -0.18000000000000002,
          0.0
        ],
        [
          -0.16000000000000003,
          0.0
        ],
        [
          -0.14,
          0.0
        ],
        [
          -0.12,
          0.0
        ],
        [
          -0.10000000000000003,
          0.0
        ],
        [
          -0.08000000000000002,
          0.0
        ],
        [
          -0.06,
          0.0
        ],
        [
          -0.040000000000000036,
          0.0
        ],
        [
          -0.020000000000000018,
          0.0
        ],
        [
          0.0,
          0.0
        ],
        [
          0.019999999999999962,
          0.0
        ],
        [
          0.03999999999999998,
          0.0
        ],
        [
          0.06,
          0.0
        ],
        [
          0.07999999999999996,
          0.0
        ],
        [
          0.09999999999999998,
          0.0
        ],
        [
          0.12,
          0.0
        ],
        [
          0.14,
          0.0
        ],
        [
          0.16000000000000003,
          0.0
        ],
        [
          0.17999999999999994,
          0.0
        ],
        [
          0.19999999999999996,
          0.0
        ],
        [
          0.21999999999999997,
          0.0
        ],
        [
          0.24,
          0.0
        ],
        [
          0.26,
          0.05000000074505806
        ],
        [
          0.28,
          0.05000000074505806
        ],
        [
          0.30000000000000004,
          0.05000000074505806
        ],
        [
          0.31999999999999995,
          0.05000000074505806
        ],
        [
          0.33999999999999997,
          0.05000000074505806
        ],
        [
          0.36,
          0.05000000074505806
        ],
        [
          0.38,
          0.05000000074505806
        ],
        [
          0.4,
          0.05000000074505806
        ],
        [
          0.42000000000000004,
          0.05000000074505806
        ],
        [
          0.43999999999999995,
          0.05000000074505806
        ],
        [
          0.45999999999999996,
          0.05000000074505806
        ],
        [
          0.48,
          0.05000000074505806
        ],
        [
          0.5,
          0.05000000074505806
        ],
        [
          0.52,
          0.05000000074505806
        ],
        [
          0.54,
          0.05000000074505806
        ],
        [
          0.5599999999999999,
          0.05000000074505806
        ],
        [
          0.58,
          0.05000000074505806
        ],
        [
          0.6,
          0.05000000074505806
        ]
      ],
      "vehicle_path_profile": [
        [
          -0.0008760771015658975,
          5.028896907788294e-07,
          0.0
        ],
        [
          0.0034395104739814997,
          -2.0819859855691902e-05,
          0.0
        ],
        [
          0.006439658347517252,
          -4.2250972910551354e-05,
          0.0
        ],
        [
          0.009441090747714043,
          -6.370930350385606e-05,
          0.0
        ],
        [
          0.012441175058484077,
          -8.515911758877337e-05,
          0.0
        ],
        [
          0.01546983141452074,
          -0.00010640599793987349,
          0.0
        ],
        [
          0.01859225519001484,
          -0.00012679096835199744,
          0.0
        ],
        [
          0.02169092185795307,
          -0.00014427368296310306,
          0.0
        ],
        [
          0.02469616010785103,
          -0.00015987458755262196,
          0.0
        ],
        [
          0.027777578681707382,
          -0.00017280901374761015,
          0.0
        ],
        [
          0.03083539754152298,
          -0.0001839974574977532,
          0.0
        ],
        [
          0.0339026004076004,
          -0.00019530579447746277,
          0.0
        ],
        [
          0.036916494369506836,
          -0.00020685089111793786,
          0.0
        ],
        [
          0.04002871736884117,
          -0.0002165139012504369,
          0.0
        ],
        [
          0.03407072648406029,
          0.00012335929204709828,
          0.0
        ],
        [
          0.04989016428589821,
          -0.00033121975138783455,
          0.0
        ],
        [
          0.05287329852581024,
          -0.0003978012828156352,
          0.0
        ],
        [
          0.055881500244140625,
          -0.00046514111454598606,
          0.0
        ],
        [
          0.05889662355184555,
          -0.000532907375600189,
          0.0
        ],
        [
          0.04826020076870918,
          0.00019948557019233704,
          0.0
        ],
        [
          0.06491678953170776,
          -0.0006691536982543766,
          0.0
        ],
        [
          0.06791063398122787,
          -0.0007370872772298753,
          0.0
        ],
        [
          0.07089269161224365,
          -0.0008045152062550187,
          0.0
        ],
        [
          0.07385193556547165,
          -0.0008705169311724603,
          0.0
        ],
        [
          0.07686121016740799,
          -0.0009375823428854346,
          0.0
        ],
        [
          0.06590171903371811,
          0.00011937280942220241,
          0.0
        ],
        [
          0.068728007376194,
          -0.00013761503214482218,
          0.0
        ],
        [
          0.0717087835073471,
          -0.00014033819024916738,
          0.0
        ],
        [
          0.07471150159835815,
          -0.00014154116797726601,
          0.0
        ],
        [
          0.077703557908535,
          -0.00015661587531212717,
          0.0
        ],
        [
          0.08068432658910751,
          -0.00015609359252266586,
          0.0
        ],
        [
          0.0836658850312233,
          -0.00016027619130909443,
          0.0
        ],
        [
          0.08663967251777649,
          -0.0001683218579273671,
          0.0
        ],
        [
          0.10382573306560516,
          -0.0015491223894059658,
          0.0
        ],
        [
          0.10682012140750885,
          -0.0016186571447178721,
          0.0
        ],
        [
          0.10982582718133926,
          -0.0016884495271369815,
          0.0
        ],
        [
          0.11283248662948608,
          -0.0017584419110789895,
          0.0
        ],
        [
          0.1015247255563736,
          -0.0001617280358914286,
          0.0
        ],
        [
          0.104405477643013,
          -0.00012230314314365387,
          0.0
        ],
        [
          0.10724495351314545,
          -0.000326416949974373,
          0.0
        ],
        [
          0.11027683317661285,
          -0.0003542834601830691,
          0.0
        ],
        [
          0.11339489370584488,
          -0.00042522986768744886,
          0.0
        ],
        [
          0.11644760519266129,
          -0.00047290936345234513,
          0.0
        ],
        [
          0.11950433999300003,
          -0.0005132753867655993,
          0.0
        ],
        [
          0.12270770221948624,
          -0.0004645898297894746,
          0.0
        ],
        [
          0.1260633021593094,
          -0.00025786508922465146,
          0.0
        ],
        [
          0.1292908936738968,
          -0.0002834094630088657,
          0.0
        ],
        [
          0.14586865901947021,
          -0.0025333415251225233,
          0.0
        ],
        [
          0.14886797964572906,
          -0.0026042810641229153,
          0.0
        ],
        [
          0.15179024636745453,
          -0.0026732657570391893,
          0.0
        ],
        [
          0.1437741369009018,
          -0.00028435286367312074,
          0.0
        ],
        [
          0.1473776400089264,
          -0.0005376111948862672,
          0.0
        ],
        [
          0.1506313532590866,
          -0.0003816886164713651,
          0.0
        ],
        [
          0.15364646911621094,
          -0.00039383932016789913,
          0.0
        ],
        [
          0.1565716564655304,
          -0.0004338920407462865,
          0.0
        ],
        [
          0.15954472124576569,
          -0.00044274155516177416,
          0.0
        ],
        [
          0.16252204775810242,
          -0.000449256447609514,
          0.0
        ],
        [
          0.17547762393951416,
          -0.003174958750605583,
          0.0
        ],
        [
          0.1784786581993103,
          -0.0032375624869018793,
          0.0
        ],
        [
          0.18147796392440796,
          -0.0033001103438436985,
          0.0
        ],
        [
          0.18447959423065186,
          -0.0033627075608819723,
          0.0
        ],
        [
          0.18747572600841522,
          -0.003425191855058074,
          0.0
        ],
        [
          0.19047586619853973,
          -0.0034877974539995193,
          0.0
        ],
        [
          0.18348251283168793,
          -0.0004895367310382426,
          0.0
        ],
        [
          0.18639056384563446,
          -0.0005285965744405985,
          0.0
        ],
        [
          0.1893625408411026,
          -0.0005014314665459096,
          0.0
        ],
        [
          0.1923263818025589,
          -0.00046926451614126563,
          0.0
        ],
        [
          0.19533026218414307,
          -0.000475755165098235,
          0.0
        ],
        [
          0.19836364686489105,
          -0.0004459562187548727,
          0.0
        ],
        [
          0.20132629573345184,
          -0.000451975385658443,
          0.0
        ],
        [
          0.2042948454618454,
          -0.0004728170461021364,
          0.0
        ],
        [
          0.20724497735500336,
          -0.0004594941856339574,
          0.0
        ],
        [
          0.21024899184703827,
          -0.0004855526494793594,
          0.0
        ],
        [
          0.2132047712802887,
          -0.0004911005962640047,
          0.0
        ],
        [
          0.2161439210176468,
          -0.000558999483473599,
          0.0
        ],
        [
          0.21917325258255005,
          -0.0005863720434717834,
          0.0
        ],
        [
          0.22209979593753815,
          -0.0005211827228777111,
          0.0
        ],
        [
          0.23543012142181396,
          -0.004432585556060076,
          0.0
        ],
        [
          0.238430917263031,
          -0.004496624227613211,
          0.0
        ],
        [
          0.2310061901807785,
          -0.0005649800295941532,
          0.0
        ],
        [
          0.2339567095041275,
          -0.0005791885196231306,
          0.0
        ],
        [
          0.23689977824687958,
          -0.0006049845251254737,
          0.0
        ],
        [
          0.2503892481327057,
          -0.00475469371303916,
          0.05000000074505806
        ],
        [
          0.2533857524394989,
          -0.0048195733688771725,
          0.05000000074505806
        ],
        [
          0.25637948513031006,
          -0.004884527530521154,
          0.05000000074505806
        ],
        [
          0.2593657970428467,
          -0.004949442110955715,
          0.05000000074505806
        ],
        [
          0.2623482644557953,
          -0.005014695227146149,
          0.05000000074505806
        ],
        [
          0.2653430104255676,
          -0.005080469883978367,
          0.05000000074505806
        ],
        [
          0.2683452367782593,
          -0.0051463814452290535,
          0.05000000074505806
        ],
        [
          0.271337628364563,
          -0.005212018266320229,
          0.05000000074505806
        ],
        [
          0.2743324935436249,
          -0.005277563817799091,
          0.05000000074505806
        ],
        [
          0.27733349800109863,
          -0.005343214143067598,
          0.05000000074505806
        ],
        [
          0.28034454584121704,
          -0.005409108474850655,
          0.05000000074505806
        ],
        [
          0.28335142135620117,
          -0.005474575329571962,
          0.05000000074505806
        ],
        [
          0.2756514251232147,
          -0.0007224611472338438,
          0.05000000074505806
        ],
        [
          0.2910967767238617,
          -0.0056902882643043995,
          0.05000000074505806
        ],
        [
          0.2940818667411804,
          -0.005795239470899105,
          0.05000000074505806
        ],
        [
          0.2970837950706482,
          -0.0059008547104895115,
          0.05000000074505806
        ],
        [
          0.3000800609588623,
          -0.006006218958646059,
          0.05000000074505806
        ],
        [
          0.3030792474746704,
          -0.006111719645559788,
          0.05000000074505806
        ]
      ],
      "spawn_pose": {
        "z": 0.062000000745058056,
        "roll": -0.0,
        "pitch": 0.0
      }
    },
    "step_10cm": {
      "seed": 1321731720,
      "step_height_m": 0.1,
      "step_x_m": 0.22,
      "row_metrics": {
        "terrain_type": "step_10cm",
        "seed": 1321731720,
        "terrain_height_delta_m": 0.10000000149011612,
        "centerline_height_delta_m": 0.10000000149011612,
        "step_transition_width_m": 0.0,
        "step_on_vehicle_path": true,
        "front_wheel_first_reach_step_time_s": 0.41999998688697815,
        "progress": 0.9940925240516663,
        "pitch_max_rad": 0.6401128172874451,
        "slip_p95": 0.5483035752821468,
        "bottom_contact_rate": 0.0,
        "q_lift": 0.27666667103767395,
        "q_pitch": 1.0,
        "q_slip": 0.39998602271080014,
        "chassis_min_clearance_m": -1.4901161415892261e-09,
        "wheel_min_clearance_m": -0.10000000149011612,
        "fail_reason": "-"
      },
      "centerline_profile": [
        [
          -0.4,
          0.0
        ],
        [
          -0.38,
          0.0
        ],
        [
          -0.36000000000000004,
          0.0
        ],
        [
          -0.34,
          0.0
        ],
        [
          -0.32,
          0.0
        ],
        [
          -0.30000000000000004,
          0.0
        ],
        [
          -0.28,
          0.0
        ],
        [
          -0.26,
          0.0
        ],
        [
          -0.24000000000000002,
          0.0
        ],
        [
          -0.22000000000000003,
          0.0
        ],
        [
          -0.2,
          0.0
        ],
        [
          -0.18000000000000002,
          0.0
        ],
        [
          -0.16000000000000003,
          0.0
        ],
        [
          -0.14,
          0.0
        ],
        [
          -0.12,
          0.0
        ],
        [
          -0.10000000000000003,
          0.0
        ],
        [
          -0.08000000000000002,
          0.0
        ],
        [
          -0.06,
          0.0
        ],
        [
          -0.040000000000000036,
          0.0
        ],
        [
          -0.020000000000000018,
          0.0
        ],
        [
          0.0,
          0.0
        ],
        [
          0.019999999999999962,
          0.0
        ],
        [
          0.03999999999999998,
          0.0
        ],
        [
          0.06,
          0.0
        ],
        [
          0.07999999999999996,
          0.0
        ],
        [
          0.09999999999999998,
          0.0
        ],
        [
          0.12,
          0.0
        ],
        [
          0.14,
          0.0
        ],
        [
          0.16000000000000003,
          0.0
        ],
        [
          0.17999999999999994,
          0.0
        ],
        [
          0.19999999999999996,
          0.0
        ],
        [
          0.21999999999999997,
          0.0
        ],
        [
          0.24,
          0.0
        ],
        [
          0.26,
          0.10000000149011612
        ],
        [
          0.28,
          0.10000000149011612
        ],
        [
          0.30000000000000004,
          0.10000000149011612
        ],
        [
          0.31999999999999995,
          0.10000000149011612
        ],
        [
          0.33999999999999997,
          0.10000000149011612
        ],
        [
          0.36,
          0.10000000149011612
        ],
        [
          0.38,
          0.10000000149011612
        ],
        [
          0.4,
          0.10000000149011612
        ],
        [
          0.42000000000000004,
          0.10000000149011612
        ],
        [
          0.43999999999999995,
          0.10000000149011612
        ],
        [
          0.45999999999999996,
          0.10000000149011612
        ],
        [
          0.48,
          0.10000000149011612
        ],
        [
          0.5,
          0.10000000149011612
        ],
        [
          0.52,
          0.10000000149011612
        ],
        [
          0.54,
          0.10000000149011612
        ],
        [
          0.5599999999999999,
          0.10000000149011612
        ],
        [
          0.58,
          0.10000000149011612
        ],
        [
          0.6,
          0.10000000149011612
        ]
      ],
      "vehicle_path_profile": [
        [
          0.0012280106311663985,
          -1.881453613350459e-06,
          0.0
        ],
        [
          0.0036314763128757477,
          -2.8372785436658887e-06,
          0.0
        ],
        [
          0.0065141222439706326,
          -3.849504537356552e-06,
          0.0
        ],
        [
          0.00950336642563343,
          -5.189959665585775e-06,
          0.0
        ],
        [
          0.01250182744115591,
          -6.594090791622875e-06,
          0.0
        ],
        [
          0.00860286969691515,
          0.00013884299551136792,
          0.0
        ],
        [
          0.018556132912635803,
          -6.701995971525321e-06,
          0.0
        ],
        [
          0.021526552736759186,
          -4.3936720430792775e-06,
          0.0
        ],
        [
          0.02455611154437065,
          -1.4031598993824446e-06,
          0.0
        ],
        [
          0.027575230225920677,
          2.1897715214436175e-06,
          0.0
        ],
        [
          0.030643483623862267,
          6.178098828968359e-06,
          0.0
        ],
        [
          0.03373159095644951,
          1.017501563183032e-05,
          0.0
        ],
        [
          0.03681740164756775,
          1.4192161870596465e-05,
          0.0
        ],
        [
          0.03998212516307831,
          1.830356995924376e-05,
          0.0
        ],
        [
          0.04313182085752487,
          2.4764869522186927e-05,
          0.0
        ],
        [
          0.046251505613327026,
          3.648399069788866e-05,
          0.0
        ],
        [
          0.04928983002901077,
          4.86154094687663e-05,
          0.0
        ],
        [
          0.052386246621608734,
          6.005666364217177e-05,
          0.0
        ],
        [
          0.013419109396636486,
          0.0001349398953607306,
          0.0
        ],
        [
          0.014273314736783504,
          8.520190021954477e-05,
          0.0
        ],
        [
          0.015176312997937202,
          8.746400999370962e-05,
          0.0
        ],
        [
          0.06461848318576813,
          7.893932342994958e-05,
          0.0
        ],
        [
          0.01691434718668461,
          9.830671478994191e-05,
          0.0
        ],
        [
          0.07081173360347748,
          8.217908907681704e-05,
          0.0
        ],
        [
          0.07391198724508286,
          8.693373820278794e-05,
          0.0
        ],
        [
          0.07700293511152267,
          9.383460565004498e-05,
          0.0
        ],
        [
          0.08009738475084305,
          0.00010266077151754871,
          0.0
        ],
        [
          0.0829790011048317,
          0.00010750959336291999,
          0.0
        ],
        [
          0.08643139153718948,
          0.00011503118003020063,
          0.0
        ],
        [
          0.02426070161163807,
          0.00019105669343844056,
          0.0
        ],
        [
          0.09263420850038528,
          0.00013819844753015786,
          0.0
        ],
        [
          0.09567226469516754,
          0.00014609981735702604,
          0.0
        ],
        [
          0.02920716069638729,
          0.00018174905562773347,
          0.0
        ],
        [
          0.10177889466285706,
          0.00015851111675146967,
          0.0
        ],
        [
          0.10482901334762573,
          0.00016329865320585668,
          0.0
        ],
        [
          0.10793311148881912,
          0.0001672539656283334,
          0.0
        ],
        [
          0.1110023707151413,
          0.0001702942099655047,
          0.0
        ],
        [
          0.11405088752508163,
          0.00017306883819401264,
          0.0
        ],
        [
          0.11680803447961807,
          0.00017784904048312455,
          0.0
        ],
        [
          0.11993744969367981,
          0.00018399189866613597,
          0.0
        ],
        [
          0.1229635551571846,
          0.0001908270496642217,
          0.0
        ],
        [
          0.048566725105047226,
          1.3234380276117008e-05,
          0.0
        ],
        [
          0.050819214433431625,
          8.750574124860577e-06,
          0.0
        ],
        [
          0.053148481994867325,
          6.149680302769411e-06,
          0.0
        ],
        [
          0.05554782599210739,
          6.201125302141008e-08,
          0.0
        ],
        [
          0.05813411995768547,
          2.535667590564117e-05,
          0.0
        ],
        [
          0.06063215807080269,
          -0.00011367247498128563,
          0.0
        ],
        [
          0.06309914588928223,
          -0.00014014868065714836,
          0.0
        ],
        [
          0.06557676196098328,
          -0.00016623166447971016,
          0.0
        ],
        [
          0.15012316405773163,
          0.0002695468720048666,
          0.0
        ],
        [
          0.07060364633798599,
          -0.0001599348324816674,
          0.0
        ],
        [
          0.07300682365894318,
          -2.7907100957236253e-05,
          0.0
        ],
        [
          0.1586020588874817,
          0.0002736186725087464,
          0.0
        ],
        [
          0.07840071618556976,
          -1.0435201147629414e-05,
          0.0
        ],
        [
          0.08109404891729355,
          1.2905588846479077e-06,
          0.0
        ],
        [
          0.16754548251628876,
          0.0002728753606788814,
          0.0
        ],
        [
          0.1705915331840515,
          0.0002739589544944465,
          0.0
        ],
        [
          0.08912554383277893,
          -8.274980064015836e-05,
          0.0
        ],
        [
          0.0920073390007019,
          -7.769255171297118e-05,
          0.0
        ],
        [
          0.09474170953035355,
          -9.975383727578446e-05,
          0.0
        ],
        [
          0.09717465192079544,
          7.066581019898877e-05,
          0.0
        ],
        [
          0.1000276580452919,
          0.00012846654863096774,
          0.0
        ],
        [
          0.10299404710531235,
          0.00013551049050875008,
          0.0
        ],
        [
          0.10596903413534164,
          0.00014339866174850613,
          0.0
        ],
        [
          0.10896646231412888,
          0.0001713872334221378,
          0.0
        ],
        [
          0.11192775517702103,
          0.00016908967518247664,
          0.0
        ],
        [
          0.20041146874427795,
          0.000264790840446949,
          0.0
        ],
        [
          0.11796056479215622,
          0.0003737662045750767,
          0.0
        ],
        [
          0.12092432379722595,
          0.00037372950464487076,
          0.0
        ],
        [
          0.20943084359169006,
          0.00025785635807551444,
          0.0
        ],
        [
          0.21239851415157318,
          0.0002559007261879742,
          0.0
        ],
        [
          0.21536332368850708,
          0.0002547701296862215,
          0.0
        ],
        [
          0.2183404564857483,
          0.0002545321185607463,
          0.0
        ],
        [
          0.13524004817008972,
          0.0002262884081574157,
          0.0
        ],
        [
          0.22439874708652496,
          0.000252399971941486,
          0.0
        ],
        [
          0.2274126410484314,
          0.00025102158542722464,
          0.0
        ],
        [
          0.23041124641895294,
          0.00024923781165853143,
          0.0
        ],
        [
          0.14719095826148987,
          4.824345523957163e-05,
          0.0
        ],
        [
          0.15020021796226501,
          6.232158921193331e-05,
          0.0
        ],
        [
          0.153366819024086,
          4.916793477605097e-05,
          0.0
        ],
        [
          0.15652376413345337,
          4.2563435272313654e-05,
          0.0
        ],
        [
          0.15973147749900818,
          -3.705282142618671e-05,
          0.0
        ],
        [
          0.1630493551492691,
          -3.4723812859738246e-05,
          0.0
        ],
        [
          0.16662053763866425,
          2.2269778128247708e-05,
          0.0
        ],
        [
          0.17049671709537506,
          6.0753096477128565e-05,
          0.0
        ],
        [
          0.2574046552181244,
          0.00023438500647898763,
          0.10000000149011612
        ],
        [
          0.17913541197776794,
          -0.00013125682016834617,
          0.0
        ],
        [
          0.18397682905197144,
          -0.0007595598581247032,
          0.0
        ],
        [
          0.2664104700088501,
          0.00022965365496929735,
          0.10000000149011612
        ],
        [
          0.19451455771923065,
          -0.000515397172421217,
          0.0
        ],
        [
          0.27241063117980957,
          0.00022650262690149248,
          0.10000000149011612
        ],
        [
          0.19929148256778717,
          0.00027095855330117047,
          0.0
        ],
        [
          0.19720719754695892,
          0.0002451457839924842,
          0.0
        ],
        [
          0.19606226682662964,
          0.0002211442479165271,
          0.0
        ],
        [
          0.19584190845489502,
          0.0001994500489672646,
          0.0
        ],
        [
          0.1965428739786148,
          0.0001797537406673655,
          0.0
        ],
        [
          0.19816482067108154,
          0.00016183743719011545,
          0.0
        ],
        [
          0.20070558786392212,
          0.00014489736349787563,
          0.0
        ],
        [
          0.20261964201927185,
          0.00014065064897295088,
          0.0
        ],
        [
          0.2994557023048401,
          0.00021232229482848197,
          0.10000000149011612
        ]
      ],
      "spawn_pose": {
        "z": 0.11200000149011612,
        "roll": -0.0,
        "pitch": 0.0
      }
    },
    "step_15cm": {
      "seed": 582883592,
      "step_height_m": 0.15,
      "step_x_m": 0.22,
      "row_metrics": {
        "terrain_type": "step_15cm",
        "seed": 582883592,
        "terrain_height_delta_m": 0.15000000596046448,
        "centerline_height_delta_m": 0.15000000596046448,
        "step_transition_width_m": 0.0,
        "step_on_vehicle_path": true,
        "front_wheel_first_reach_step_time_s": 0.3999999761581421,
        "progress": 0.9899611274401348,
        "pitch_max_rad": 0.13279087841510773,
        "slip_p95": 0.9988018570050464,
        "bottom_contact_rate": 0.12,
        "q_lift": 0.2874999940395355,
        "q_pitch": 0.34583440413729705,
        "q_slip": 1.0,
        "chassis_min_clearance_m": -0.05000000447034836,
        "wheel_min_clearance_m": -0.15000000596046448,
        "fail_reason": "-"
      },
      "centerline_profile": [
        [
          -0.4,
          0.0
        ],
        [
          -0.38,
          0.0
        ],
        [
          -0.36000000000000004,
          0.0
        ],
        [
          -0.34,
          0.0
        ],
        [
          -0.32,
          0.0
        ],
        [
          -0.30000000000000004,
          0.0
        ],
        [
          -0.28,
          0.0
        ],
        [
          -0.26,
          0.0
        ],
        [
          -0.24000000000000002,
          0.0
        ],
        [
          -0.22000000000000003,
          0.0
        ],
        [
          -0.2,
          0.0
        ],
        [
          -0.18000000000000002,
          0.0
        ],
        [
          -0.16000000000000003,
          0.0
        ],
        [
          -0.14,
          0.0
        ],
        [
          -0.12,
          0.0
        ],
        [
          -0.10000000000000003,
          0.0
        ],
        [
          -0.08000000000000002,
          0.0
        ],
        [
          -0.06,
          0.0
        ],
        [
          -0.040000000000000036,
          0.0
        ],
        [
          -0.020000000000000018,
          0.0
        ],
        [
          0.0,
          0.0
        ],
        [
          0.019999999999999962,
          0.0
        ],
        [
          0.03999999999999998,
          0.0
        ],
        [
          0.06,
          0.0
        ],
        [
          0.07999999999999996,
          0.0
        ],
        [
          0.09999999999999998,
          0.0
        ],
        [
          0.12,
          0.0
        ],
        [
          0.14,
          0.0
        ],
        [
          0.16000000000000003,
          0.0
        ],
        [
          0.17999999999999994,
          0.0
        ],
        [
          0.19999999999999996,
          0.0
        ],
        [
          0.21999999999999997,
          0.0
        ],
        [
          0.24,
          0.0
        ],
        [
          0.26,
          0.15000000596046448
        ],
        [
          0.28,
          0.15000000596046448
        ],
        [
          0.30000000000000004,
          0.15000000596046448
        ],
        [
          0.31999999999999995,
          0.15000000596046448
        ],
        [
          0.33999999999999997,
          0.15000000596046448
        ],
        [
          0.36,
          0.15000000596046448
        ],
        [
          0.38,
          0.15000000596046448
        ],
        [
          0.4,
          0.15000000596046448
        ],
        [
          0.42000000000000004,
          0.15000000596046448
        ],
        [
          0.43999999999999995,
          0.15000000596046448
        ],
        [
          0.45999999999999996,
          0.15000000596046448
        ],
        [
          0.48,
          0.15000000596046448
        ],
        [
          0.5,
          0.15000000596046448
        ],
        [
          0.52,
          0.15000000596046448
        ],
        [
          0.54,
          0.15000000596046448
        ],
        [
          0.5599999999999999,
          0.15000000596046448
        ],
        [
          0.58,
          0.15000000596046448
        ],
        [
          0.6,
          0.15000000596046448
        ]
      ],
      "vehicle_path_profile": [
        [
          0.0010547183919698,
          -2.978734073622036e-06,
          0.0
        ],
        [
          -0.006943208165466785,
          1.934628016897477e-06,
          0.0
        ],
        [
          -0.009165695868432522,
          2.5774374989850912e-06,
          0.0
        ],
        [
          -0.011388185434043407,
          3.2191373975365423e-06,
          0.0
        ],
        [
          -0.013610683381557465,
          3.859708158415742e-06,
          0.0
        ],
        [
          -0.010681993328034878,
          -0.0011588853085413575,
          0.0
        ],
        [
          -0.006483358796685934,
          -0.002612465526908636,
          0.0
        ],
        [
          -0.0042678541503846645,
          -0.003510092617943883,
          0.0
        ],
        [
          -0.005209015682339668,
          -0.0035463322419673204,
          0.0
        ],
        [
          -0.006014351267367601,
          -0.0035179059486836195,
          0.0
        ],
        [
          -0.006670080590993166,
          -0.0035196910612285137,
          0.0
        ],
        [
          -0.007178348023444414,
          -0.003477875143289566,
          0.0
        ],
        [
          0.03704493120312691,
          -0.00010516444308450446,
          0.0
        ],
        [
          -0.008106333203613758,
          -0.0036739930510520935,
          0.0
        ],
        [
          -0.008469718508422375,
          -0.003689120290800929,
          0.0
        ],
        [
          0.0460459403693676,
          -0.00013064932136330754,
          0.0
        ],
        [
          -0.009077705442905426,
          -0.0036882590502500534,
          0.0
        ],
        [
          0.05204588174819946,
          -0.00014763687795493752,
          0.0
        ],
        [
          0.05504584312438965,
          -0.0001561305543873459,
          0.0
        ],
        [
          0.05804578959941864,
          -0.0001646241289563477,
          0.0
        ],
        [
          0.061045750975608826,
          -0.00017311767442151904,
          0.0
        ],
        [
          0.06404569745063782,
          -0.00018161108891945332,
          0.0
        ],
        [
          0.067045658826828,
          -0.0001901045034173876,
          0.0
        ],
        [
          0.07004562020301819,
          -0.00019859790336340666,
          0.0
        ],
        [
          0.07304557412862778,
          -0.0002070913033094257,
          0.0
        ],
        [
          0.07604553550481796,
          -0.0002155846159439534,
          0.0
        ],
        [
          -0.010527994483709335,
          -0.003737648483365774,
          0.0
        ],
        [
          -0.010580652393400669,
          -0.0037376692052930593,
          0.0
        ],
        [
          -0.010629592463374138,
          -0.0037369532510638237,
          0.0
        ],
        [
          -0.010675029829144478,
          -0.0037371066864579916,
          0.0
        ],
        [
          -0.010716496035456657,
          -0.0037386748008430004,
          0.0
        ],
        [
          0.09404543042182922,
          -0.00026654452085494995,
          0.0
        ],
        [
          -0.010788601823151112,
          -0.0037383479066193104,
          0.0
        ],
        [
          0.10004539042711258,
          -0.0002835311461240053,
          0.0
        ],
        [
          -0.010849426500499249,
          -0.0037402857560664415,
          0.0
        ],
        [
          -0.01087548490613699,
          -0.003740055253729224,
          0.0
        ],
        [
          -0.01089922059327364,
          -0.0037402810994535685,
          0.0
        ],
        [
          0.11204537004232407,
          -0.00031750454218126833,
          0.0
        ],
        [
          0.11504536122083664,
          -0.0003259978839196265,
          0.0
        ],
        [
          -0.010959490202367306,
          -0.003741401946172118,
          0.0
        ],
        [
          0.12104532867670059,
          -0.0003429844800848514,
          0.0
        ],
        [
          -0.01099163293838501,
          -0.0037417737767100334,
          0.0
        ],
        [
          0.12704528868198395,
          -0.00035997095983475447,
          0.0
        ],
        [
          -0.011018062010407448,
          -0.0037426974158734083,
          0.0
        ],
        [
          -0.011029773391783237,
          -0.00374275422655046,
          0.0
        ],
        [
          -0.011040706187486649,
          -0.0037432783283293247,
          0.0
        ],
        [
          -0.011050652712583542,
          -0.003744447370991111,
          0.0
        ],
        [
          -0.01105948444455862,
          -0.0037444368936121464,
          0.0
        ],
        [
          -0.011067885905504227,
          -0.0037445875350385904,
          0.0
        ],
        [
          -0.011075837537646294,
          -0.0037452748510986567,
          0.0
        ],
        [
          0.15104517340660095,
          -0.0004279169370420277,
          0.0
        ],
        [
          -0.011089416220784187,
          -0.0037465684581547976,
          0.0
        ],
        [
          -0.01109567191451788,
          -0.0037467130459845066,
          0.0
        ],
        [
          -0.011101830750703812,
          -0.00374729186296463,
          0.0
        ],
        [
          -0.011107717640697956,
          -0.0037488858215510845,
          0.0
        ],
        [
          -0.01111259963363409,
          -0.003748831804841757,
          0.0
        ],
        [
          -0.011117641814053059,
          -0.0037489242386072874,
          0.0
        ],
        [
          -0.011122865602374077,
          -0.003749564755707979,
          0.0
        ],
        [
          -0.011127880774438381,
          -0.003751372918486595,
          0.0
        ],
        [
          -0.011131909675896168,
          -0.0037510700058192015,
          0.0
        ],
        [
          0.1810450255870819,
          -0.0005128493648953736,
          0.0
        ],
        [
          0.18404501676559448,
          -0.0005213426193222404,
          0.0
        ],
        [
          0.18704499304294586,
          -0.0005298358737491071,
          0.0
        ],
        [
          -0.011150664649903774,
          -0.003752912627533078,
          0.0
        ],
        [
          -0.011155146174132824,
          -0.0037524967920035124,
          0.0
        ],
        [
          -0.011160769499838352,
          -0.0037531559355556965,
          0.0
        ],
        [
          0.19904494285583496,
          -0.0005638088332489133,
          0.0
        ],
        [
          0.20204491913318634,
          -0.0005723020876757801,
          0.0
        ],
        [
          -0.011174295097589493,
          -0.003753436729311943,
          0.0
        ],
        [
          -0.011180240660905838,
          -0.0037540236953645945,
          0.0
        ],
        [
          -0.011185946874320507,
          -0.0037565468810498714,
          0.0
        ],
        [
          0.21404477953910828,
          -0.0006062748143449426,
          0.0
        ],
        [
          -0.011194593273103237,
          -0.003754126839339733,
          0.0
        ],
        [
          -0.01120169647037983,
          -0.0037549822591245174,
          0.0
        ],
        [
          -0.011207041330635548,
          -0.0037581257056444883,
          0.0
        ],
        [
          -0.011209370568394661,
          -0.0037567918188869953,
          0.0
        ],
        [
          -0.011213052086532116,
          -0.0037555317394435406,
          0.0
        ],
        [
          -0.011220823973417282,
          -0.003756973659619689,
          0.0
        ],
        [
          -0.011227564886212349,
          -0.0037605594843626022,
          0.0
        ],
        [
          -0.011228848248720169,
          -0.003759475192055106,
          0.0
        ],
        [
          0.24104338884353638,
          -0.0006827046745456755,
          0.0
        ],
        [
          0.24404333531856537,
          -0.0006911967066116631,
          0.0
        ],
        [
          0.24704328179359436,
          -0.0006996887386776507,
          0.0
        ],
        [
          0.25004318356513977,
          -0.0007081806543283165,
          0.15000000596046448
        ],
        [
          -0.01138387806713581,
          -0.0037832267116755247,
          0.0
        ],
        [
          -0.011350085027515888,
          -0.003788198111578822,
          0.0
        ],
        [
          0.2590429186820984,
          -0.0007336564594879746,
          0.15000000596046448
        ],
        [
          0.2620428502559662,
          -0.0007421483751386404,
          0.15000000596046448
        ],
        [
          0.2650427520275116,
          -0.0007506402907893062,
          0.15000000596046448
        ],
        [
          -0.01126679964363575,
          -0.003789566457271576,
          0.0
        ],
        [
          0.2710425853729248,
          -0.0007676241802982986,
          0.15000000596046448
        ],
        [
          0.2740424871444702,
          -0.0007761160959489644,
          0.15000000596046448
        ],
        [
          0.277042418718338,
          -0.0007846080115996301,
          0.15000000596046448
        ],
        [
          -0.011217652820050716,
          -0.0037904565688222647,
          0.0
        ],
        [
          -0.01120893657207489,
          -0.003791743889451027,
          0.0
        ],
        [
          0.28604215383529663,
          -0.0008100838167592883,
          0.15000000596046448
        ],
        [
          -0.011193061247467995,
          -0.003789999522268772,
          0.0
        ],
        [
          -0.011186860501766205,
          -0.003790039336308837,
          0.0
        ],
        [
          -0.011180917732417583,
          -0.003791077760979533,
          0.0
        ],
        [
          0.29804185032844543,
          -0.000844051013700664,
          0.15000000596046448
        ]
      ],
      "spawn_pose": {
        "z": 0.1620000059604645,
        "roll": -0.0,
        "pitch": 0.0
      }
    }
  }
}