{
  "meta": {
    "seed": 20260426,
    "repeats": 5,
    "vehicles": [
      "city_small",
      "offroad_medium",
      "mountain_large"
    ],
    "terrains": [
      "flat",
      "slope_forward_20deg",
      "cross_slope_20deg",
      "step_15cm_approach",
      "pit_medium_approach",
      "trench_forward",
      "bump_field"
    ],
    "sample_count": 105,
    "combo_count": 21
  },
  "rows": [
    {
      "vehicle_type": "city_small",
      "terrain_type": "flat",
      "gate_pass_rate": 1.0,
      "initialization_invalid_rate": 0.0,
      "settle_time_mean": 0.12239840719999506,
      "settle_time_p95": 0.12432545899999922,
      "roll_expected_mean": 0.0,
      "roll_actual_mean": 0.0021011615074961127,
      "roll_error_mean": 0.0021011615074961127,
      "roll_error_p95": 0.005252903768740281,
      "pitch_expected_mean": 0.0,
      "pitch_actual_mean": -0.004662745309479802,
      "pitch_error_mean": 0.004662745309479802,
      "pitch_error_p95": 0.011656863273699506,
      "linear_speed_mean": 0.0003025303004757239,
      "linear_speed_p95": 0.00039189604451081683,
      "angular_speed_mean": 1.6931929470350388e-05,
      "angular_speed_p95": 4.2329823675875966e-05,
      "bottom_before_action_rate": 0.0,
      "lift_before_action_rate": 0.0,
      "message_time_valid_rate": 1.0,
      "error_distribution": {
        "none": 5
      }
    },
    {
      "vehicle_type": "city_small",
      "terrain_type": "slope_forward_20deg",
      "gate_pass_rate": 0.0,
      "initialization_invalid_rate": 1.0,
      "settle_time_mean": 0.14814878340000065,
      "settle_time_p95": 0.14856760580000242,
      "roll_expected_mean": 1.1125729364260076e-15,
      "roll_actual_mean": 0.09610517270932462,
      "roll_error_mean": 0.09610517270932609,
      "roll_error_p95": 0.24026293177331523,
      "pitch_expected_mean": -24.463768183263973,
      "pitch_actual_mean": -8.023781459503422,
      "pitch_error_mean": 1.7617258138021732,
      "pitch_error_p95": 4.404314534505433,
      "linear_speed_mean": 2.1977619676827338e-05,
      "linear_speed_p95": 3.735927472350861e-05,
      "angular_speed_mean": 4.9420438396433716e-05,
      "angular_speed_p95": 8.236739732738952e-05,
      "bottom_before_action_rate": 0.0,
      "lift_before_action_rate": 0.6,
      "message_time_valid_rate": 1.0,
      "error_distribution": {
        "start_gate_failed": 5
      }
    },
    {
      "vehicle_type": "city_small",
      "terrain_type": "cross_slope_20deg",
      "gate_pass_rate": 0.0,
      "initialization_invalid_rate": 1.0,
      "settle_time_mean": 0.14808412920000363,
      "settle_time_p95": 0.1482438917999957,
      "roll_expected_mean": 15.088615952102455,
      "roll_actual_mean": 0.0,
      "roll_error_mean": 0.0,
      "roll_error_p95": 0.0,
      "pitch_expected_mean": -1.2952063497756703e-15,
      "pitch_actual_mean": 0.0,
      "pitch_error_mean": 0.0,
      "pitch_error_p95": 0.0,
      "linear_speed_mean": 1.8918217392630533e-07,
      "linear_speed_p95": 1.8918217392630533e-07,
      "angular_speed_mean": 1.516147878848517e-06,
      "angular_speed_p95": 1.516147878848517e-06,
      "bottom_before_action_rate": 0.0,
      "lift_before_action_rate": 0.0,
      "message_time_valid_rate": 1.0,
      "error_distribution": {
        "start_gate_failed": 5
      }
    },
    {
      "vehicle_type": "city_small",
      "terrain_type": "step_15cm_approach",
      "gate_pass_rate": 0.0,
      "initialization_invalid_rate": 1.0,
      "settle_time_mean": 0.13621432040000628,
      "settle_time_p95": 0.13631860479999885,
      "roll_expected_mean": 9.57520895704661e-15,
      "roll_actual_mean": -0.02910784317231051,
      "roll_error_mean": 0.029107843172316704,
      "roll_error_p95": 0.07276960793079176,
      "pitch_expected_mean": -25.11483576110873,
      "pitch_actual_mean": -7.253990835094855,
      "pitch_error_mean": 2.791943469348637,
      "pitch_error_p95": 6.979858673371592,
      "linear_speed_mean": 0.00016021340640515555,
      "linear_speed_p95": 0.00016065454671677432,
      "angular_speed_mean": 0.0007327974890358746,
      "angular_speed_p95": 0.0012213291483931243,
      "bottom_before_action_rate": 0.0,
      "lift_before_action_rate": 0.4,
      "message_time_valid_rate": 1.0,
      "error_distribution": {
        "start_gate_failed": 5
      }
    },
    {
      "vehicle_type": "city_small",
      "terrain_type": "pit_medium_approach",
      "gate_pass_rate": 0.0,
      "initialization_invalid_rate": 1.0,
      "settle_time_mean": 0.1441202295999915,
      "settle_time_p95": 0.14422583799998848,
      "roll_expected_mean": -0.025482226576838844,
      "roll_actual_mean": 0.10735761706842126,
      "roll_error_mean": 0.1328398436452601,
      "roll_error_p95": 0.4549126948505253,
      "pitch_expected_mean": 4.436053227781562,
      "pitch_actual_mean": 2.1396704583871413,
      "pitch_error_mean": 4.801302395056077,
      "pitch_error_p95": 5.897049896879626,
      "linear_speed_mean": 6.3404906541111145e-06,
      "linear_speed_p95": 7.925613317638893e-06,
      "angular_speed_mean": 4.6894161237613046e-05,
      "angular_speed_p95": 5.8617701547016306e-05,
      "bottom_before_action_rate": 0.0,
      "lift_before_action_rate": 0.0,
      "message_time_valid_rate": 1.0,
      "error_distribution": {
        "start_gate_failed": 5
      }
    },
    {
      "vehicle_type": "city_small",
      "terrain_type": "trench_forward",
      "gate_pass_rate": 1.0,
      "initialization_invalid_rate": 0.0,
      "settle_time_mean": 0.13209706060000598,
      "settle_time_p95": 0.132241204200011,
      "roll_expected_mean": 0.0,
      "roll_actual_mean": -0.004925386654388599,
      "roll_error_mean": 0.004925386654388598,
      "roll_error_p95": 0.01970154661755439,
      "pitch_expected_mean": 0.0,
      "pitch_actual_mean": 0.2513334005661897,
      "pitch_error_mean": 0.2513334005661897,
      "pitch_error_p95": 1.0053336022647588,
      "linear_speed_mean": 0.00020090676612044951,
      "linear_speed_p95": 0.0007998552459123221,
      "angular_speed_mean": 0.0012481237812666673,
      "angular_speed_p95": 0.004992435879065969,
      "bottom_before_action_rate": 0.0,
      "lift_before_action_rate": 0.0,
      "message_time_valid_rate": 1.0,
      "error_distribution": {
        "none": 5
      }
    },
    {
      "vehicle_type": "city_small",
      "terrain_type": "bump_field",
      "gate_pass_rate": 1.0,
      "initialization_invalid_rate": 0.0,
      "settle_time_mean": 0.13995610880002687,
      "settle_time_p95": 0.14008914760004246,
      "roll_expected_mean": -0.32881006666468193,
      "roll_actual_mean": -0.2747962065883265,
      "roll_error_mean": 0.3405582199212644,
      "roll_error_p95": 0.35818044980613617,
      "pitch_expected_mean": -1.9823993894627059,
      "pitch_actual_mean": -0.931043634531154,
      "pitch_error_mean": 1.3275235124236953,
      "pitch_error_p95": 1.9823993894627057,
      "linear_speed_mean": 0.004465135158594852,
      "linear_speed_p95": 0.011115858001440913,
      "angular_speed_mean": 7.526857189077426e-05,
      "angular_speed_p95": 0.0001254476198179571,
      "bottom_before_action_rate": 0.0,
      "lift_before_action_rate": 0.0,
      "message_time_valid_rate": 1.0,
      "error_distribution": {
        "none": 5
      }
    },
    {
      "vehicle_type": "offroad_medium",
      "terrain_type": "flat",
      "gate_pass_rate": 1.0,
      "initialization_invalid_rate": 0.0,
      "settle_time_mean": 0.15231175399999303,
      "settle_time_p95": 0.15238652339999134,
      "roll_expected_mean": 0.0,
      "roll_actual_mean": 0.0,
      "roll_error_mean": 0.0,
      "roll_error_p95": 0.0,
      "pitch_expected_mean": 0.0,
      "pitch_actual_mean": 0.0,
      "pitch_error_mean": 0.0,
      "pitch_error_p95": 0.0,
      "linear_speed_mean": 0.0,
      "linear_speed_p95": 0.0,
      "angular_speed_mean": 0.0,
      "angular_speed_p95": 0.0,
      "bottom_before_action_rate": 0.0,
      "lift_before_action_rate": 0.0,
      "message_time_valid_rate": 1.0,
      "error_distribution": {
        "none": 5
      }
    },
    {
      "vehicle_type": "offroad_medium",
      "terrain_type": "slope_forward_20deg",
      "gate_pass_rate": 0.0,
      "initialization_invalid_rate": 1.0,
      "settle_time_mean": 0.1880651655999827,
      "settle_time_p95": 0.188199518399972,
      "roll_expected_mean": 1.3744872660299246e-15,
      "roll_actual_mean": -0.0028036806949713884,
      "roll_error_mean": 0.0028036806949727046,
      "roll_error_p95": 0.011214722779890817,
      "pitch_expected_mean": -16.872997123786817,
      "pitch_actual_mean": -3.973389168705687,
      "pitch_error_mean": 0.5987897439483227,
      "pitch_error_p95": 2.39515897579329,
      "linear_speed_mean": 2.5091407459460802e-05,
      "linear_speed_p95": 4.1904692839826164e-05,
      "angular_speed_mean": 7.425486627552231e-05,
      "angular_speed_p95": 9.281858284440289e-05,
      "bottom_before_action_rate": 0.0,
      "lift_before_action_rate": 0.0,
      "message_time_valid_rate": 1.0,
      "error_distribution": {
        "start_gate_failed": 5
      }
    },
    {
      "vehicle_type": "offroad_medium",
      "terrain_type": "cross_slope_20deg",
      "gate_pass_rate": 0.0,
      "initialization_invalid_rate": 1.0,
      "settle_time_mean": 0.19234822199999826,
      "settle_time_p95": 0.1924689336000142,
      "roll_expected_mean": 19.77233171040342,
      "roll_actual_mean": 7.972832736316361,
      "roll_error_mean": 0.06390005215499275,
      "roll_error_p95": 0.15975013038748187,
      "pitch_expected_mean": 3.6457962189144115e-15,
      "pitch_actual_mean": 0.0016059065379939647,
      "pitch_error_mean": 0.0016059065379920964,
      "pitch_error_p95": 0.004014766344980241,
      "linear_speed_mean": 8.584774899548136e-06,
      "linear_speed_p95": 1.1951232918119577e-05,
      "angular_speed_mean": 3.430711027855664e-05,
      "angular_speed_p95": 5.717851713092774e-05,
      "bottom_before_action_rate": 0.0,
      "lift_before_action_rate": 0.0,
      "message_time_valid_rate": 1.0,
      "error_distribution": {
        "start_gate_failed": 5
      }
    },
    {
      "vehicle_type": "offroad_medium",
      "terrain_type": "step_15cm_approach",
      "gate_pass_rate": 0.0,
      "initialization_invalid_rate": 1.0,
      "settle_time_mean": 0.040158463000000214,
      "settle_time_p95": 0.04060237979999783,
      "roll_expected_mean": -2.8923169134558854e-15,
      "roll_actual_mean": -0.0014163019861181234,
      "roll_error_mean": 0.0014163019861168809,
      "roll_error_p95": 0.003540754965292202,
      "pitch_expected_mean": -17.354025284440603,
      "pitch_actual_mean": -14.237507468684928,
      "pitch_error_mean": 7.295897354908684,
      "pitch_error_p95": 18.23974338727171,
      "linear_speed_mean": 3.777931851799413e-07,
      "linear_speed_p95": 7.514499884565768e-07,
      "angular_speed_mean": 4.899324446829785e-07,
      "angular_speed_p95": 8.803908713181607e-07,
      "bottom_before_action_rate": 0.0,
      "lift_before_action_rate": 0.4,
      "message_time_valid_rate": 1.0,
      "error_distribution": {
        "start_gate_failed": 5
      }
    },
    {
      "vehicle_type": "offroad_medium",
      "terrain_type": "pit_medium_approach",
      "gate_pass_rate": 1.0,
      "initialization_invalid_rate": 0.0,
      "settle_time_mean": 0.16058350600002314,
      "settle_time_p95": 0.1609228650000091,
      "roll_expected_mean": -0.07513166518713159,
      "roll_actual_mean": 0.0,
      "roll_error_mean": 0.07513166518713159,
      "roll_error_p95": 0.0751316651871316,
      "pitch_expected_mean": 0.1712792206997686,
      "pitch_actual_mean": 0.0,
      "pitch_error_mean": 0.1712792206997686,
      "pitch_error_p95": 0.17127922069976861,
      "linear_speed_mean": 0.00018988887222804094,
      "linear_speed_p95": 0.00035173543892597244,
      "angular_speed_mean": 0.0007397216792508716,
      "angular_speed_p95": 0.0015560930433473287,
      "bottom_before_action_rate": 0.0,
      "lift_before_action_rate": 0.0,
      "message_time_valid_rate": 1.0,
      "error_distribution": {
        "none": 5
      }
    },
    {
      "vehicle_type": "offroad_medium",
      "terrain_type": "trench_forward",
      "gate_pass_rate": 1.0,
      "initialization_invalid_rate": 0.0,
      "settle_time_mean": 0.15221919960000604,
      "settle_time_p95": 0.15246982500001421,
      "roll_expected_mean": 0.0,
      "roll_actual_mean": 0.0,
      "roll_error_mean": 0.0,
      "roll_error_p95": 0.0,
      "pitch_expected_mean": 0.0,
      "pitch_actual_mean": 0.0,
      "pitch_error_mean": 0.0,
      "pitch_error_p95": 0.0,
      "linear_speed_mean": 0.0,
      "linear_speed_p95": 0.0,
      "angular_speed_mean": 0.0,
      "angular_speed_p95": 0.0,
      "bottom_before_action_rate": 0.0,
      "lift_before_action_rate": 0.0,
      "message_time_valid_rate": 1.0,
      "error_distribution": {
        "none": 5
      }
    },
    {
      "vehicle_type": "offroad_medium",
      "terrain_type": "bump_field",
      "gate_pass_rate": 1.0,
      "initialization_invalid_rate": 0.0,
      "settle_time_mean": 0.16423100600001134,
      "settle_time_p95": 0.16433022519995574,
      "roll_expected_mean": -1.0819554916074552,
      "roll_actual_mean": -1.4544382245606475,
      "roll_error_mean": 0.37248273295319256,
      "roll_error_p95": 0.37380849196869714,
      "pitch_expected_mean": -0.0471880476423368,
      "pitch_actual_mean": -0.44858001042314644,
      "pitch_error_mean": 0.4013919627808097,
      "pitch_error_p95": 0.41371880869655697,
      "linear_speed_mean": 0.005787416752602701,
      "linear_speed_p95": 0.013497912957242383,
      "angular_speed_mean": 0.0,
      "angular_speed_p95": 0.0,
      "bottom_before_action_rate": 0.0,
      "lift_before_action_rate": 0.0,
      "message_time_valid_rate": 1.0,
      "error_distribution": {
        "none": 5
      }
    },
    {
      "vehicle_type": "mountain_large",
      "terrain_type": "flat",
      "gate_pass_rate": 1.0,
      "initialization_invalid_rate": 0.0,
      "settle_time_mean": 0.18064442819999157,
      "settle_time_p95": 0.181010904999971,
      "roll_expected_mean": 0.0,
      "roll_actual_mean": -6.649074320248955e-06,
      "roll_error_mean": 6.649074320248954e-06,
      "roll_error_p95": 2.6596297280995808e-05,
      "pitch_expected_mean": 0.0,
      "pitch_actual_mean": -5.945566506040887e-05,
      "pitch_error_mean": 5.9455665060408884e-05,
      "pitch_error_p95": 0.00023782266024163548,
      "linear_speed_mean": 5.8632042527415844e-05,
      "linear_speed_p95": 0.00011417797118301912,
      "angular_speed_mean": 0.00011139265604889935,
      "angular_speed_p95": 0.00013857942521457463,
      "bottom_before_action_rate": 0.0,
      "lift_before_action_rate": 0.0,
      "message_time_valid_rate": 1.0,
      "error_distribution": {
        "none": 5
      }
    },
    {
      "vehicle_type": "mountain_large",
      "terrain_type": "slope_forward_20deg",
      "gate_pass_rate": 0.0,
      "initialization_invalid_rate": 1.0,
      "settle_time_mean": 0.2126182098000072,
      "settle_time_p95": 0.21300732300003347,
      "roll_expected_mean": 2.4741314340364084e-16,
      "roll_actual_mean": -0.0012891177194137827,
      "roll_error_mean": 0.0012891177194137564,
      "roll_error_p95": 0.003222794298534391,
      "pitch_expected_mean": -19.403754360406374,
      "pitch_actual_mean": -7.9953760847597,
      "pitch_error_mean": 0.23387434059715195,
      "pitch_error_p95": 0.5846858514928799,
      "linear_speed_mean": 2.3533605170180396e-05,
      "linear_speed_p95": 3.02080127951349e-05,
      "angular_speed_mean": 1.619099004363513e-05,
      "angular_speed_p95": 2.698498340605855e-05,
      "bottom_before_action_rate": 0.0,
      "lift_before_action_rate": 0.6,
      "message_time_valid_rate": 1.0,
      "error_distribution": {
        "start_gate_failed": 5
      }
    },
    {
      "vehicle_type": "mountain_large",
      "terrain_type": "cross_slope_20deg",
      "gate_pass_rate": 0.0,
      "initialization_invalid_rate": 1.0,
      "settle_time_mean": 0.20848697459996401,
      "settle_time_p95": 0.20872370159993353,
      "roll_expected_mean": 17.148776310897247,
      "roll_actual_mean": 4.005748139429907,
      "roll_error_mean": 0.03140870859313384,
      "roll_error_p95": 0.12563483437253536,
      "pitch_expected_mean": -1.859879046152689e-15,
      "pitch_actual_mean": 0.005453277991003616,
      "pitch_error_mean": 0.005453277991003921,
      "pitch_error_p95": 0.021813111964015676,
      "linear_speed_mean": 1.032076397678307e-06,
      "linear_speed_p95": 1.2900954970978838e-06,
      "angular_speed_mean": 8.585629984915774e-08,
      "angular_speed_p95": 1.0732037481144718e-07,
      "bottom_before_action_rate": 0.0,
      "lift_before_action_rate": 0.0,
      "message_time_valid_rate": 1.0,
      "error_distribution": {
        "start_gate_failed": 5
      }
    },
    {
      "vehicle_type": "mountain_large",
      "terrain_type": "step_15cm_approach",
      "gate_pass_rate": 1.0,
      "initialization_invalid_rate": 0.0,
      "settle_time_mean": 0.07617240080001011,
      "settle_time_p95": 0.07632407819999117,
      "roll_expected_mean": -3.151047582367908e-15,
      "roll_actual_mean": 0.12615277460815183,
      "roll_error_mean": 0.12615277460815502,
      "roll_error_p95": 0.12615277460815502,
      "pitch_expected_mean": -13.600543037022131,
      "pitch_actual_mean": -15.270144910187648,
      "pitch_error_mean": 1.669601873165518,
      "pitch_error_p95": 1.6696018731655178,
      "linear_speed_mean": 0.01863161254834323,
      "linear_speed_p95": 0.01863161254834323,
      "angular_speed_mean": 0.01312877769398749,
      "angular_speed_p95": 0.01312877769398749,
      "bottom_before_action_rate": 0.0,
      "lift_before_action_rate": 1.0,
      "message_time_valid_rate": 1.0,
      "error_distribution": {
        "none": 5
      }
    },
    {
      "vehicle_type": "mountain_large",
      "terrain_type": "pit_medium_approach",
      "gate_pass_rate": 1.0,
      "initialization_invalid_rate": 0.0,
      "settle_time_mean": 0.18405834759998924,
      "settle_time_p95": 0.18433265099997698,
      "roll_expected_mean": -0.15640115396533105,
      "roll_actual_mean": -0.36736748198352853,
      "roll_error_mean": 0.21096632801819748,
      "roll_error_p95": 0.21096632801819748,
      "pitch_expected_mean": 0.056812641338159706,
      "pitch_actual_mean": 0.5011898358607161,
      "pitch_error_mean": 0.4443771945225564,
      "pitch_error_p95": 0.4443771945225564,
      "linear_speed_mean": 0.017162621752616018,
      "linear_speed_p95": 0.017162621752616018,
      "angular_speed_mean": 0.042123231461776794,
      "angular_speed_p95": 0.042123231461776794,
      "bottom_before_action_rate": 0.0,
      "lift_before_action_rate": 0.0,
      "message_time_valid_rate": 1.0,
      "error_distribution": {
        "none": 5
      }
    },
    {
      "vehicle_type": "mountain_large",
      "terrain_type": "trench_forward",
      "gate_pass_rate": 1.0,
      "initialization_invalid_rate": 0.0,
      "settle_time_mean": 0.18089381280001363,
      "settle_time_p95": 0.18149524559999008,
      "roll_expected_mean": 0.0,
      "roll_actual_mean": -1.329814864049791e-05,
      "roll_error_mean": 1.3298148640497907e-05,
      "roll_error_p95": 3.324537160124477e-05,
      "pitch_expected_mean": 0.0,
      "pitch_actual_mean": -0.00011891133012081774,
      "pitch_error_mean": 0.00011891133012081777,
      "pitch_error_p95": 0.0002972783253020444,
      "linear_speed_mean": 7.714735207928361e-05,
      "linear_speed_p95": 0.00013269328073488691,
      "angular_speed_mean": 8.420588688322408e-05,
      "angular_speed_p95": 0.00013857942521457463,
      "bottom_before_action_rate": 0.0,
      "lift_before_action_rate": 0.0,
      "message_time_valid_rate": 1.0,
      "error_distribution": {
        "none": 5
      }
    },
    {
      "vehicle_type": "mountain_large",
      "terrain_type": "bump_field",
      "gate_pass_rate": 1.0,
      "initialization_invalid_rate": 0.0,
      "settle_time_mean": 0.1843888560000096,
      "settle_time_p95": 0.184510714799967,
      "roll_expected_mean": -0.6276679273765473,
      "roll_actual_mean": -1.004579502101523,
      "roll_error_mean": 0.37691157472497566,
      "roll_error_p95": 0.37691157472497566,
      "pitch_expected_mean": 0.16917006582081048,
      "pitch_actual_mean": -0.4110326752880208,
      "pitch_error_mean": 0.5802027411088312,
      "pitch_error_p95": 0.5802027411088312,
      "linear_speed_mean": 0.0005204679295003451,
      "linear_speed_p95": 0.0005204679295003451,
      "angular_speed_mean": 0.0,
      "angular_speed_p95": 0.0,
      "bottom_before_action_rate": 0.0,
      "lift_before_action_rate": 0.0,
      "message_time_valid_rate": 1.0,
      "error_distribution": {
        "none": 5
      }
    }
  ]
}